synthgen/__init__.py
synthgen/exceptions.py
synthgen/models.py
synthgen/sync_client.py
synthgen_client-0.0.7.dist-info/METADATA
synthgen_client-0.0.7.dist-info/WHEEL
synthgen_client-0.0.7.dist-info/RECORD
