Metadata-Version: 2.4
Name: synthgen-client
Version: 0.0.7
Summary: A Python client library for the Synthetic Data Generation API
Project-URL: Homepage, https://github.com/nasirus/synthgen-client
Project-URL: Repository, https://github.com/nasirus/synthgen-client.git
Project-URL: Documentation, https://github.com/nasirus/synthgen-client#readme
Author-email: nasirus <email@example.com>
License-Expression: MIT
Keywords: api,client,data,generation,synthetic
Classifier: Development Status :: 3 - Alpha
Classifier: Intended Audience :: Developers
Classifier: License :: OSI Approved :: MIT License
Classifier: Programming Language :: Python :: 3
Classifier: Programming Language :: Python :: 3.8
Classifier: Programming Language :: Python :: 3.9
Classifier: Programming Language :: Python :: 3.10
Classifier: Programming Language :: Python :: 3.11
Classifier: Programming Language :: Python :: 3.12
Requires-Python: >=3.8
Requires-Dist: httpx>=0.24.0
Requires-Dist: pydantic>=2.0.0
Requires-Dist: rich>=13.9.4
